social_auth_core-4.8.2.dist-info/licenses/LICENSE
social_core/__init__.py
social_core/actions.py
social_core/exceptions.py
social_core/py.typed
social_core/storage.py
social_core/store.py
social_core/strategy.py
social_core/utils.py
social_core/backends/__init__.py
social_core/backends/amazon.py
social_core/backends/angel.py
social_core/backends/apple.py
social_core/backends/appsfuel.py
social_core/backends/arcgis.py
social_core/backends/asana.py
social_core/backends/atlassian.py
social_core/backends/auth0.py
social_core/backends/auth0_openidconnect.py
social_core/backends/azuread.py
social_core/backends/azuread_b2c.py
social_core/backends/azuread_tenant.py
social_core/backends/base.py
social_core/backends/battlenet.py
social_core/backends/beats.py
social_core/backends/behance.py
social_core/backends/belgiumeid.py
social_core/backends/bitbucket.py
social_core/backends/bitbucket_datacenter.py
social_core/backends/box.py
social_core/backends/bungie.py
social_core/backends/cas.py
social_core/backends/changetip.py
social_core/backends/chatwork.py
social_core/backends/cilogon.py
social_core/backends/classlink.py
social_core/backends/clef.py
social_core/backends/clever.py
social_core/backends/coding.py
social_core/backends/cognito.py
social_core/backends/coinbase.py
social_core/backends/coursera.py
social_core/backends/dailymotion.py
social_core/backends/deezer.py
social_core/backends/digitalocean.py
social_core/backends/discogs.py
social_core/backends/discord.py
social_core/backends/discourse.py
social_core/backends/disqus.py
social_core/backends/docker.py
social_core/backends/douban.py
social_core/backends/dribbble.py
social_core/backends/drip.py
social_core/backends/dropbox.py
social_core/backends/echosign.py
social_core/backends/edmodo.py
social_core/backends/egi_checkin.py
social_core/backends/einfracz.py
social_core/backends/elixir.py
social_core/backends/email.py
social_core/backends/etsy.py
social_core/backends/eventbrite.py
social_core/backends/eveonline.py
social_core/backends/evernote.py
social_auth_core-4.8.2.dist-info/METADATA
social_auth_core-4.8.2.dist-info/WHEEL
social_auth_core-4.8.2.dist-info/top_level.txt
social_auth_core-4.8.2.dist-info/RECORD
